pynodo/__init__.py
zenapi/__init__.py
pynodo-0.2.2.dist-info/LICENSE
pynodo-0.2.2.dist-info/METADATA
pynodo-0.2.2.dist-info/WHEEL
pynodo-0.2.2.dist-info/top_level.txt
pynodo-0.2.2.dist-info/RECORD
