Metadata-Version: 2.1
Name: pynodo
Version: 0.2.2
Summary: Python wrapper for Zenodo REST API
Home-page: https://github.com/tpall/zenapi
Author: Taavi Päll
Author-email: tapa741@gmail.com
License: UNKNOWN
Platform: UNKNOWN
Classifier: Programming Language :: Python :: 3
Classifier: License :: OSI Approved :: MIT License
Classifier: Operating System :: OS Independent
Requires-Python: >=3.5
Requires-Dist: requests
